pretty_colors/__init__.py
pretty_colors/colors.py
pretty_colors/mc.py
pretty_colors-0.1.1.dist-info/METADATA
pretty_colors-0.1.1.dist-info/WHEEL
pretty_colors-0.1.1.dist-info/top_level.txt
pretty_colors-0.1.1.dist-info/RECORD
