Metadata-Version: 2.4
Name: pretty_colors
Version: 0.1.1
Summary: A package for working with colors, including retrieval, random selection without repeats, and hex-to-RGB conversion.
Home-page: https://github.com/dd2912/pretty_colors
Author: Dave
Author-email: your.email@example.com
Classifier: Programming Language :: Python :: 3
Classifier: License :: OSI Approved :: MIT License
Classifier: Operating System :: OS Independent
Requires-Python: >=3.6
Dynamic: author
Dynamic: author-email
Dynamic: classifier
Dynamic: description
Dynamic: description-content-type
Dynamic: home-page
Dynamic: requires-python
Dynamic: summary
